javaccflab
