Metadata-Version: 2.1
Name: javaccflab
Version: 0.1.3
Summary: JavaCCF is utility to fix style in Java files
Home-page: https://github.com/tochanenko/MetaProgramming/tree/lab-2
Author: Vladislav Tochanenko
Author-email: itochanenko@gmail.com
License: UNKNOWN
Platform: UNKNOWN
